twimer/__init__.py
twimer/database.py
twimer/twimer.py
twimer/twitter_connection.py
Twimer-0.0.5.dist-info/LICENSE
Twimer-0.0.5.dist-info/METADATA
Twimer-0.0.5.dist-info/WHEEL
Twimer-0.0.5.dist-info/top_level.txt
Twimer-0.0.5.dist-info/RECORD
