Metadata-Version: 2.1
Name: Twimer
Version: 0.0.5
Summary: Stream Tweets into Your Favorite Databases
Home-page: https://github.com/mkareshk/twimer
Author: Moein Kareshk
Author-email: mkareshk@outlook.com
License: UNKNOWN
Platform: UNKNOWN
Classifier: Programming Language :: Python :: 3
Classifier: License :: OSI Approved :: MIT License
Classifier: Operating System :: OS Independent
Requires-Python: >=3.8
Requires-Dist: pymongo (==4.0.1)
Requires-Dist: tweepy (==3.9.0)
Provides-Extra: testing
Requires-Dist: pytest ; extra == 'testing'
Requires-Dist: pytest-runner ; extra == 'testing'
